mcp_gigapi/__init__.py
mcp_gigapi/__main__.py
mcp_gigapi/client.py
mcp_gigapi/config.py
mcp_gigapi/mcp_server.py
mcp_gigapi/tools.py
mcp_gigapi-1.1.4.dist-info/METADATA
mcp_gigapi-1.1.4.dist-info/WHEEL
mcp_gigapi-1.1.4.dist-info/entry_points.txt
mcp_gigapi-1.1.4.dist-info/RECORD
