Metadata-Version: 2.4
Name: mcp-gigapi
Version: 1.1.4
Summary: An MCP server for GigAPI Timeseries Lake
Project-URL: Homepage, https://github.com/gigapi/mcp-gigapi
Project-URL: Repository, https://github.com/gigapi/mcp-gigapi
Project-URL: Issues, https://github.com/gigapi/mcp-gigapi/issues
Author-email: GigAPI MCP Team <team@gigapi.com>
License: Apache-2.0
Keywords: database,gigapi,mcp,timeseries
Classifier: Development Status :: 3 - Alpha
Classifier: Intended Audience :: Developers
Classifier: License :: OSI Approved :: Apache Software License
Classifier: Programming Language :: Python :: 3
Classifier: Programming Language :: Python :: 3.10
Classifier: Programming Language :: Python :: 3.11
Classifier: Programming Language :: Python :: 3.12
Classifier: Programming Language :: Python :: 3.13
Requires-Python: >=3.10
Requires-Dist: fastmcp>=2.0.0
Requires-Dist: mcp>=1.0.0
Requires-Dist: pydantic>=2.0.0
Requires-Dist: python-dotenv>=1.0.0
Requires-Dist: requests>=2.31.0
Provides-Extra: dev
Requires-Dist: black>=23.0.0; extra == 'dev'
Requires-Dist: fastmcp>=0.1.0; extra == 'dev'
Requires-Dist: mypy>=1.0.0; extra == 'dev'
Requires-Dist: pytest-asyncio>=0.21.0; extra == 'dev'
Requires-Dist: pytest>=7.0.0; extra == 'dev'
Requires-Dist: ruff>=0.1.0; extra == 'dev'
